bigquery_manager/__init__.py
bigquery_manager/client.py
bigquery_manager/manager.py
bigquery_manager-1.0.2.dist-info/METADATA
bigquery_manager-1.0.2.dist-info/WHEEL
bigquery_manager-1.0.2.dist-info/licenses/LICENSE
bigquery_manager-1.0.2.dist-info/RECORD
